<annotation>
	<folder>kottu</folder>
	<filename>output_2620412440.jpg</filename>
	<path>D:\IIT\Group Project\SDGP data\kottu\output_2620412440.jpg</path>
	<source>
		<database>Unknown</database>
	</source>
	<size>
		<width>900</width>
		<height>675</height>
		<depth>3</depth>
	</size>
	<segmented>0</segmented>
	<object>
		<name>kottu</name>
		<pose>Unspecified</pose>
		<truncated>0</truncated>
		<difficult>0</difficult>
		<bndbox>
			<xmin>406</xmin>
			<ymin>186</ymin>
			<xmax>670</xmax>
			<ymax>535</ymax>
		</bndbox>
	</object>
</annotation>
