<annotation>
	<folder>kottu</folder>
	<filename>yimg_spKDpz.jpg</filename>
	<path>D:\IIT\Group Project\SDGP data\kottu\yimg_spKDpz.jpg</path>
	<source>
		<database>Unknown</database>
	</source>
	<size>
		<width>4000</width>
		<height>3000</height>
		<depth>3</depth>
	</size>
	<segmented>0</segmented>
	<object>
		<name>kottu</name>
		<pose>Unspecified</pose>
		<truncated>0</truncated>
		<difficult>0</difficult>
		<bndbox>
			<xmin>660</xmin>
			<ymin>1603</ymin>
			<xmax>1476</xmax>
			<ymax>2619</ymax>
		</bndbox>
	</object>
	<object>
		<name>kottu</name>
		<pose>Unspecified</pose>
		<truncated>0</truncated>
		<difficult>0</difficult>
		<bndbox>
			<xmin>1554</xmin>
			<ymin>144</ymin>
			<xmax>2632</xmax>
			<ymax>944</ymax>
		</bndbox>
	</object>
	<object>
		<name>kottu</name>
		<pose>Unspecified</pose>
		<truncated>0</truncated>
		<difficult>0</difficult>
		<bndbox>
			<xmin>2504</xmin>
			<ymin>1647</ymin>
			<xmax>3513</xmax>
			<ymax>2641</ymax>
		</bndbox>
	</object>
</annotation>
